chat_ai_client/__init__.py
chat_ai_client-0.0.1.dist-info/LICENSE
chat_ai_client-0.0.1.dist-info/METADATA
chat_ai_client-0.0.1.dist-info/WHEEL
chat_ai_client-0.0.1.dist-info/top_level.txt
chat_ai_client-0.0.1.dist-info/RECORD
