Metadata-Version: 2.1
Name: chat-ai-client
Version: 0.0.1
Summary: Chat.ai API Client
Home-page: https://github.com/chat-ai/chat-ai-client-python
Author: Marc Hadfield
Author-email: marc@vital.ai
License: Apache License 2.0
Classifier: Programming Language :: Python :: 3.10
Classifier: License :: OSI Approved :: Apache Software License
Classifier: Operating System :: OS Independent
Requires-Python: >=3.10
License-File: LICENSE
Requires-Dist: vital-ai-vitalsigns
Requires-Dist: vital-ai-domain
Requires-Dist: vital-ai-aimp
